{
  "modules": [
    {
      "name": "FileSrc",
      "description": "Источник данных — читает сигнал из файла. Использует mmap для эффективного чтения. Читает блоками заданного размера. Поддерживает вещественный и комплексный форматы.",
      "fields": [
        {
          "name": "file name",
          "type": "string",
          "label": "Путь к файлу"
        },
        {
          "name": "max size",
          "type": "int",
          "label": "Максимальный размер блока, байты"
        },
        {
          "name": "data type",
          "type": "enum",
          "label": "Формат данных: float или complex"
        }
      ]
    }
  ]
}
